{
  "code": 0,
  "data": {
    "categories": [
      {
        "id": 174,
        "name": "鸭肠"
      },
      {
        "id": 4,
        "name": "鸡胸"
      },
      {
        "id": 147,
        "name": "翅膀类"
      },
      {
        "id": 304,
        "name": "鸡皮"
      },
      {
        "id": 317,
        "name": "鸡胗"
      },
      {
        "id": 319,
        "name": "鸡肚"
      },
      {
        "id": 73,
        "name": "鸡边腿"
      },
      {
        "id": 77,
        "name": "琵琶腿"
      },
      {
        "id": 79,
        "name": "鸡排腿"
      },
      {
        "id": 295,
        "name": "鸡爪类"
      },
      {
        "id": 313,
        "name": "掌中宝"
      }
    ]
  },
  "message": "OK"
}