{
  "code":0,
  "data":{
    "identity_data":{
      "name":"姓名",
      "id_card":"身份证号",
      "front_image":"身份证正面图像",
      "reverse_image":"身份证反面图像",
      "portrait":"肖像图像",
      "image_status":{"front_image":10,"reverse_image":10,"portrait":1},
      "status":5,
      "fail":0
    },
    "image_data":{
      "firm_license":["fsdfsfd"],
      "store_images":["fsfsf","sfs","public/XXX.jpg"],
      "store_contract":["fsfsf","sfs","public/XXX.jpg"],
      "credit_report":["fsfsf","sfs","public/XXX.jpg"],
      "status":5
    },
    "contacts":[
      {
        "name":"姓名",
        "relation":"COUPLE",
        "mobile_code":"手机号码"
      }
    ],
    "bank_data":{
      "debit_card":{
        "bank_code":"CMB",
        "card_number":"银行卡号码",
        "mobile_code":"开户手机号码",
        "open_bank_province":"100010",
        "open_bank_city":"100011",
        "open_bank_branch":"开户行支行"
      },
      "credit_card":{
        "bank_code":"CMB",
        "card_number":"银行卡号码",
        "limit":10000.00,
        "mobile_code":"开户手机号码",
        "valid_time":"01/19"
      }
    },
    "final_protocol":{
      "register_protocol":1,
      "privacy_protocol":1
    }
  },
  "message":"OK"
}